pokerpy/__init__.py
pokerpy/constants/__init__.py
pokerpy/constants/_action_constants.py
pokerpy/constants/_card_constants.py
pokerpy/constants/_logging_constants.py
pokerpy/logger/__init__.py
pokerpy/logger/_logger.py
pokerpy/managers/__init__.py
pokerpy/managers/_betting_round/_action_is_valid.py
pokerpy/managers/_betting_round/_alternate_players.py
pokerpy/managers/_betting_round/_betting_round.py
pokerpy/managers/_betting_round/_wait_for_player.py
pokerpy/messages/__init__.py
pokerpy/messages/_error_messages.py
pokerpy/structures/__init__.py
pokerpy/structures/_action.py
pokerpy/structures/_card.py
pokerpy/structures/_player.py
pokerpy/structures/_table.py
pokerpy/structures/_hand/_arrange_cards.py
pokerpy/structures/_hand/_get_category.py
pokerpy/structures/_hand/_hand.py
pokerpy-0.5.0.dist-info/licenses/LICENSE.txt
pokerpy-0.5.0.dist-info/licenses/NOTICE.txt
pokerpy-0.5.0.dist-info/METADATA
pokerpy-0.5.0.dist-info/WHEEL
pokerpy-0.5.0.dist-info/top_level.txt
pokerpy-0.5.0.dist-info/RECORD
