Metadata-Version: 2.4
Name: pokerpy
Version: 0.5.0
Summary: Python poker playability framework (under development)
Home-page: https://github.com/jorsaland/pokerpy
Download-URL: https://github.com/jorsaland/pokerpy/archive/refs/tags/0.5.0.tar.gz
Author: Andrés Saldarriaga Jordan
Author-email: andresaldarriaga.94@gmail.com
Maintainer: Andrés Saldarriaga Jordan
Maintainer-email: andresaldarriaga.94@gmail.com
Classifier: License :: OSI Approved :: Apache Software License
Classifier: Programming Language :: Python :: 3.12
Classifier: Operating System :: OS Independent
License-File: LICENSE.txt
License-File: NOTICE.txt
Dynamic: author
Dynamic: author-email
Dynamic: classifier
Dynamic: description
Dynamic: description-content-type
Dynamic: download-url
Dynamic: home-page
Dynamic: license-file
Dynamic: maintainer
Dynamic: maintainer-email
Dynamic: summary
